fixtopt/__init__.py
fixtopt/fixtopt.py
fixtopt_xtofl-0.1.4.dist-info/LICENSE
fixtopt_xtofl-0.1.4.dist-info/WHEEL
fixtopt_xtofl-0.1.4.dist-info/METADATA
fixtopt_xtofl-0.1.4.dist-info/RECORD
