Metadata-Version: 2.1
Name: fixtopt-xtofl
Version: 0.1.4
Summary: Pytest extension for adding test options
License: MIT
Author: xtofl
Author-email: xtofl@fixtopt.com
Requires-Python: >=3.8,<4.0
Classifier: License :: OSI Approved :: MIT License
Classifier: Operating System :: OS Independent
Classifier: Programming Language :: Python :: 3
Classifier: Programming Language :: Python :: 3.10
Classifier: Programming Language :: Python :: 3.8
Classifier: Programming Language :: Python :: 3.9
Classifier: Topic :: Software Development :: Libraries :: Python Modules
Classifier: Topic :: Software Development :: Testing
Requires-Dist: pytest (>=6.2.4,<8)
